{
    "hiragana": [
      {"jpn": "が", "eng": "ga"},
      {"jpn": "ぎ", "eng": "gi"},
      {"jpn": "ぐ", "eng": "gu"},
      {"jpn": "げ", "eng": "ge"},
      {"jpn": "ご", "eng": "go"},
      {"jpn": "ざ", "eng": "za"},
      {"jpn": "じ", "eng": "ji"},
      {"jpn": "ず", "eng": "zu"},
      {"jpn": "ぜ", "eng": "ze"},
      {"jpn": "ぞ", "eng": "zo"},
      {"jpn": "だ", "eng": "da"},
      {"jpn": "ぢ", "eng": "ji"},
      {"jpn": "づ", "eng": "zu"},
      {"jpn": "で", "eng": "de"},
      {"jpn": "ど", "eng": "do"},
      {"jpn": "ば", "eng": "ba"},
      {"jpn": "び", "eng": "bi"},
      {"jpn": "ぶ", "eng": "bu"},
      {"jpn": "べ", "eng": "be"},
      {"jpn": "ぼ", "eng": "bo"},
      {"jpn": "ぱ", "eng": "pa"},
      {"jpn": "ぴ", "eng": "pi"},
      {"jpn": "ぷ", "eng": "pu"},
      {"jpn": "ぺ", "eng": "pe"},
      {"jpn": "ぽ", "eng": "po"},
      {"jpn": "きゃ", "eng": "kya"},
      {"jpn": "きゅ", "eng": "kyu"},
      {"jpn": "きょ", "eng": "kyo"},
      {"jpn": "しゃ", "eng": "sha"},
      {"jpn": "しゅ", "eng": "shu"},
      {"jpn": "しょ", "eng": "sho"},
      {"jpn": "ちゃ", "eng": "cha"},
      {"jpn": "ちゅ", "eng": "chu"},
      {"jpn": "ちょ", "eng": "cho"},
      {"jpn": "にゃ", "eng": "nya"},
      {"jpn": "にゅ", "eng": "nyu"},
      {"jpn": "にょ", "eng": "nyo"},
      {"jpn": "ひゃ", "eng": "hya"},
      {"jpn": "ひゅ", "eng": "hyu"},
      {"jpn": "ひょ", "eng": "hyo"},
      {"jpn": "みゃ", "eng": "mya"},
      {"jpn": "みゅ", "eng": "myu"},
      {"jpn": "みょ", "eng": "myo"},
      {"jpn": "りゃ", "eng": "rya"},
      {"jpn": "りゅ", "eng": "ryu"},
      {"jpn": "りょ", "eng": "ryo"},
      {"jpn": "ん", "eng": "n"}
    ],
    "katakana": [
      {"jpn": "ガ", "eng": "ga"},
      {"jpn": "ギ", "eng": "gi"},
      {"jpn": "グ", "eng": "gu"},
      {"jpn": "ゲ", "eng": "ge"},
      {"jpn": "ゴ", "eng": "go"},
      {"jpn": "ザ", "eng": "za"},
      {"jpn": "ジ", "eng": "ji"},
      {"jpn": "ズ", "eng": "zu"},
      {"jpn": "ゼ", "eng": "ze"},
      {"jpn": "ゾ", "eng": "zo"},
      {"jpn": "ダ", "eng": "da"},
      {"jpn": "ヂ", "eng": "ji"},
      {"jpn": "ヅ", "eng": "zu"},
      {"jpn": "デ", "eng": "de"},
      {"jpn": "ド", "eng": "do"},
      {"jpn": "バ", "eng": "ba"},
      {"jpn": "ビ", "eng": "bi"},
      {"jpn": "ブ", "eng": "bu"},
      {"jpn": "ベ", "eng": "be"},
      {"jpn": "ボ", "eng": "bo"},
      {"jpn": "パ", "eng": "pa"},
      {"jpn": "ピ", "eng": "pi"},
      {"jpn": "プ", "eng": "pu"},
      {"jpn": "ペ", "eng": "pe"},
      {"jpn": "ポ", "eng": "po"},
      {"jpn": "キャ", "eng": "kya"},
      {"jpn": "キュ", "eng": "kyu"},
      {"jpn": "キョ", "eng": "kyo"},
      {"jpn": "シャ", "eng": "sha"},
      {"jpn": "シュ", "eng": "shu"},
      {"jpn": "ショ", "eng": "sho"},
      {"jpn": "チャ", "eng": "cha"},
      {"jpn": "チュ", "eng": "chu"},
      {"jpn": "チョ", "eng": "cho"},
      {"jpn": "ニャ", "eng": "nya"},
      {"jpn": "ニュ", "eng": "nyu"},
      {"jpn": "ニョ", "eng": "nyo"},
      {"jpn": "ヒャ", "eng": "hya"},
      {"jpn": "ヒュ", "eng": "hyu"},
      {"jpn": "ヒョ", "eng": "hyo"},
      {"jpn": "ミャ", "eng": "mya"},
      {"jpn": "ミュ", "eng": "myu"},
      {"jpn": "ミョ", "eng": "myo"},
      {"jpn": "リャ", "eng": "rya"},
      {"jpn": "リュ", "eng": "ryu"},
      {"jpn": "リョ", "eng": "ryo"},
      {"jpn": "ン", "eng": "n"}
    ]
  }
  